ctf_utils.py
superstes_ctf_tools-1.0.4.dist-info/LICENSE.txt
superstes_ctf_tools-1.0.4.dist-info/METADATA
superstes_ctf_tools-1.0.4.dist-info/WHEEL
superstes_ctf_tools-1.0.4.dist-info/top_level.txt
superstes_ctf_tools-1.0.4.dist-info/RECORD
