Metadata-Version: 2.1
Name: superstes-ctf-tools
Version: 1.0.4
Summary: Some python utils and scripts that I find useful for security challenges
Home-page: https://github.com/superstes/ctf-tools
Author: René Rath
Author-email: contact@superstes.eu
Project-URL: Repository, https://github.com/superstes/ctf-tools
Project-URL: Bug Tracker, https://github.com/superstes/ctf-tools/issues
Classifier: Programming Language :: Python :: 3
Classifier: License :: OSI Approved :: GNU General Public License v3 (GPLv3)
Classifier: Operating System :: OS Independent
Requires-Python: >=3.3
License-File: LICENSE.txt
